ament_cmake_ros/_dummy.cpython-313-x86_64-linux-gnu.so
ros_ament_cmake_ros-0.14.5.data/data/share/ament_cmake_ros/local_setup.bash
ros_ament_cmake_ros-0.14.5.data/data/share/ament_cmake_ros/local_setup.dsv
ros_ament_cmake_ros-0.14.5.data/data/share/ament_cmake_ros/local_setup.sh
ros_ament_cmake_ros-0.14.5.data/data/share/ament_cmake_ros/local_setup.zsh
ros_ament_cmake_ros-0.14.5.data/data/share/ament_cmake_ros/package.dsv
ros_ament_cmake_ros-0.14.5.data/data/share/ament_cmake_ros/package.xml
ros_ament_cmake_ros-0.14.5.data/data/share/ament_cmake_ros/cmake/ament_add_ros_isolated_gmock.cmake
ros_ament_cmake_ros-0.14.5.data/data/share/ament_cmake_ros/cmake/ament_add_ros_isolated_gtest.cmake
ros_ament_cmake_ros-0.14.5.data/data/share/ament_cmake_ros/cmake/ament_add_ros_isolated_pytest.cmake
ros_ament_cmake_ros-0.14.5.data/data/share/ament_cmake_ros/cmake/ament_add_ros_isolated_test.cmake
ros_ament_cmake_ros-0.14.5.data/data/share/ament_cmake_ros/cmake/ament_cmake_export_dependencies-extras.cmake
ros_ament_cmake_ros-0.14.5.data/data/share/ament_cmake_ros/cmake/ament_cmake_ros-extras.cmake
ros_ament_cmake_ros-0.14.5.data/data/share/ament_cmake_ros/cmake/ament_cmake_rosConfig-version.cmake
ros_ament_cmake_ros-0.14.5.data/data/share/ament_cmake_ros/cmake/ament_cmake_rosConfig.cmake
ros_ament_cmake_ros-0.14.5.data/data/share/ament_cmake_ros/cmake/run_test_isolated.py
ros_ament_cmake_ros-0.14.5.data/data/share/ament_cmake_ros/environment/ament_prefix_path.dsv
ros_ament_cmake_ros-0.14.5.data/data/share/ament_cmake_ros/environment/ament_prefix_path.sh
ros_ament_cmake_ros-0.14.5.data/data/share/ament_cmake_ros/environment/path.dsv
ros_ament_cmake_ros-0.14.5.data/data/share/ament_cmake_ros/environment/path.sh
ros_ament_cmake_ros-0.14.5.data/data/share/ament_index/resource_index/package_run_dependencies/ament_cmake_ros
ros_ament_cmake_ros-0.14.5.data/data/share/ament_index/resource_index/packages/ament_cmake_ros
ros_ament_cmake_ros-0.14.5.dist-info/METADATA
ros_ament_cmake_ros-0.14.5.dist-info/WHEEL
ros_ament_cmake_ros-0.14.5.dist-info/top_level.txt
ros_ament_cmake_ros-0.14.5.dist-info/RECORD
