Metadata-Version: 2.4
Name: ros-ament-cmake-ros
Version: 0.14.5
Summary: Wheel for the ament_cmake_ros (ros-ament-cmake-ros) ROS 2 package.
Requires-Dist: ros-rmw-test-fixture-implementation~=0.14.5
Dynamic: description
Dynamic: description-content-type
Dynamic: requires-dist
Dynamic: summary
